examples/traffic_control.v
module traffic_control(
    input wire clk,
    input wire reset,
    output reg [1:0] light
);


parameter RED = 2'b00;
parameter YELLOW = 2'b01;
parameter GREEN = 2'b10;

parameter RED_TIME = 10;
parameter YELLOW_TIME = 10;
parameter GREEN_TIME = 10;

reg [1:0] state, next_state;
reg [5:0] timer;

always @(posedge clk or posedge reset) begin
    if (reset)
        state <= RED;
    else
        state <= next_state;
end

always @(*) begin
    case (state)
        RED:
            if (timer == RED_TIME - 1)
                next_state = GREEN;
            else
                next_state = RED;
        YELLOW:
            if (timer == YELLOW_TIME - 1)
                next_state = RED;
            else
                next_state = YELLOW;
        GREEN:
            if (timer == GREEN_TIME - 1)
                next_state = YELLOW;
            else
                next_state = GREEN;
        default: next_state = RED;
    endcase
end

always @(posedge clk or posedge reset) begin
    if (reset)
        timer <= 0;
    else if ((state == RED && timer == RED_TIME - 1) ||
             (state == YELLOW && timer == YELLOW_TIME - 1) ||
             (state == GREEN && timer == GREEN_TIME - 1))
        timer <= 0;
    else
        timer <= timer + 1;
end

always @(*) begin
    light = state;
end

endmodule

yug/traffic light/traffic_tb.v
`timescale 1ns/1ns

module traffic_tb; 
    reg clk; 
    reg reset; 
    wire [1:0] light; 

traffic_control uut (
    .clk(clk),
    .reset(reset),
    .light(light)
);

initial begin 
    clk = 0;
    forever #5 clk = ~clk; 
end 

initial begin 
    $dumpfile("traffic_control.vcd");
    $dumpvars(0, traffic_tb);

    reset = 1;
    #10 reset = 0;

    #1000; 

    $finish; 
end

always @(posedge clk) begin 
    $display("Time=%0t, Light=%b", $time, light); 
end
endmodule

traffic/traffic_control.vcd
$date
	Tue Jul 16 00:25:00 2024
$end
$version
	Icarus Verilog
$end
$timescale
	1ns
$end
$scope module traffic_tb $end
$var wire 2 ! light [1:0] $end
$var reg 1 " clk $end
$var reg 1 # reset $end
$scope module uut $end
$var wire 1 " clk $end
$var wire 1 # reset $end
$var reg 2 $ light [1:0] $end
$var reg 2 % next_state [1:0] $end
$var reg 2 & state [1:0] $end
$var reg 6 ' timer [5:0] $end
$upscope $end
$upscope $end
$enddefinitions $end
#0
$dumpvars
b0 '
b0 &
b0 %
b0 $
1#
0"
b0 !
$end
#5
1"
#10
0"
0#
#15
b1 '
1"
#20
0"
#25
b10 '
1"
#30
0"
#35
b11 '
1"
#40
0"
#45
b100 '
1"
#50
0"
#55
b101 '
1"
#60
0"
#65
b110 '
1"
#70
0"
#75
b111 '
1"
#80
0"
#85
b1000 '
1"
#90
0"
#95
b10 %
b1001 '
1"
#100
0"
#105
b10 !
b10 $
b0 '
b10 &
1"
#110
0"
#115
b1 '
1"
#120
0"
#125
b10 '
1"
#130
0"
#135
b11 '
1"
#140
0"
#145
b100 '
1"
#150
0"
#155
b101 '
1"
#160
0"
#165
b110 '
1"
#170
0"
#175
b111 '
1"
#180
0"
#185
b1000 '
1"
#190
0"
#195
b1 %
b1001 '
1"
#200
0"
#205
b1 !
b1 $
b0 '
b1 &
1"
#210
0"
#215
b1 '
1"
#220
0"
#225
b10 '
1"
#230
0"
#235
b11 '
1"
#240
0"
#245
b100 '
1"
#250
0"
#255
b101 '
1"
#260
0"
#265
b110 '
1"
#270
0"
#275
b111 '
1"
#280
0"
#285
b1000 '
1"
#290
0"
#295
b0 %
b1001 '
1"
#300
0"
#305
b0 !
b0 $
b0 '
b0 &
1"
#310
0"
#315
b1 '
1"
#320
0"
#325
b10 '
1"
#330
0"
#335
b11 '
1"
#340
0"
#345
b100 '
1"
#350
0"
#355
b101 '
1"
#360
0"
#365
b110 '
1"
#370
0"
#375
b111 '
1"
#380
0"
#385
b1000 '
1"
#390
0"
#395
b10 %
b1001 '
1"
#400
0"
#405
b10 !
b10 $
b0 '
b10 &
1"
#410
0"
#415
b1 '
1"
#420
0"
#425
b10 '
1"
#430
0"
#435
b11 '
1"
#440
0"
#445
b100 '
1"
#450
0"
#455
b101 '
1"
#460
0"
#465
b110 '
1"
#470
0"
#475
b111 '
1"
#480
0"
#485
b1000 '
1"
#490
0"
#495
b1 %
b1001 '
1"
#500
0"
#505
b1 !
b1 $
b0 '
b1 &
1"
#510
0"
#515
b1 '
1"
#520
0"
#525
b10 '
1"
#530
0"
#535
b11 '
1"
#540
0"
#545
b100 '
1"
#550
0"
#555
b101 '
1"
#560
0"
#565
b110 '
1"
#570
0"
#575
b111 '
1"
#580
0"
#585
b1000 '
1"
#590
0"
#595
b0 %
b1001 '
1"
#600
0"
#605
b0 !
b0 $
b0 '
b0 &
1"
#610
0"
#615
b1 '
1"
#620
0"
#625
b10 '
1"
#630
0"
#635
b11 '
1"
#640
0"
#645
b100 '
1"
#650
0"
#655
b101 '
1"
#660
0"
#665
b110 '
1"
#670
0"
#675
b111 '
1"
#680
0"
#685
b1000 '
1"
#690
0"
#695
b10 %
b1001 '
1"
#700
0"
#705
b10 !
b10 $
b0 '
b10 &
1"
#710
0"
#715
b1 '
1"
#720
0"
#725
b10 '
1"
#730
0"
#735
b11 '
1"
#740
0"
#745
b100 '
1"
#750
0"
#755
b101 '
1"
#760
0"
#765
b110 '
1"
#770
0"
#775
b111 '
1"
#780
0"
#785
b1000 '
1"
#790
0"
#795
b1 %
b1001 '
1"
#800
0"
#805
b1 !
b1 $
b0 '
b1 &
1"
#810
0"
#815
b1 '
1"
#820
0"
#825
b10 '
1"
#830
0"
#835
b11 '
1"
#840
0"
#845
b100 '
1"
#850
0"
#855
b101 '
1"
#860
0"
#865
b110 '
1"
#870
0"
#875
b111 '
1"
#880
0"
#885
b1000 '
1"
#890
0"
#895
b0 %
b1001 '
1"
#900
0"
#905
b0 !
b0 $
b0 '
b0 &
1"
#910
0"
#915
b1 '
1"
#920
0"
#925
b10 '
1"
#930
0"
#935
b11 '
1"
#940
0"
#945
b100 '
1"
#950
0"
#955
b101 '
1"
#960
0"
#965
b110 '
1"
#970
0"
#975
b111 '
1"
#980
0"
#985
b1000 '
1"
#990
0"
#995
b10 %
b1001 '
1"
#1000
0"
#1005
b10 !
b10 $
b0 '
b10 &
1"
