examples/water_control.v
module water_reservoir_controller (
    input wire S1,
    input wire S2,
    input wire S3,
    input wire clk,
    input wire reset,
    output reg FR1,
    output reg FR2,
    output reg FR3,
    output reg AFR
);

parameter [1:0] ABOVE_S3 = 2'b00,
                BETWEEN_S3_S2 = 2'b01,
                BETWEEN_S2_S1 = 2'b10,
                BELOW_S1 = 2'b11;

reg [1:0] current_state, next_state;

always @(*) begin
    case (current_state)
        ABOVE_S3: 
            if (!S3) next_state = BETWEEN_S3_S2;
            else next_state = ABOVE_S3;
        BETWEEN_S3_S2:
            if (S3) next_state = ABOVE_S3;
            else if (!S2) next_state = BETWEEN_S2_S1;
            else next_state = BETWEEN_S3_S2;
        BETWEEN_S2_S1:
            if (S2) next_state = BETWEEN_S3_S2;
            else if (!S1) next_state = BELOW_S1;
            else next_state = BETWEEN_S2_S1;
        BELOW_S1:
            if (S1) next_state = BETWEEN_S2_S1;
            else next_state = BELOW_S1;
        default:
            next_state = ABOVE_S3;
    endcase
end

always @(posedge clk or posedge reset) begin
    if (reset)
        current_state <= ABOVE_S3;
    else
        current_state <= next_state;
end

always @(*) begin
    FR1 = 0;
    FR2 = 0;
    FR3 = 0;
    AFR = 0;
    case (current_state)
        ABOVE_S3: begin
            FR1 = 0;
            FR2 = 0;
            FR3 = 0;
            AFR = 0;
        end
        BETWEEN_S3_S2: begin
            FR1 = 1;
            FR2 = 0;
            FR3 = 0;
            AFR = 0;
        end
        BETWEEN_S2_S1: begin
            FR1 = 1;
            FR2 = 1;
            FR3 = 0;
            AFR = 0;
        end
        BELOW_S1: begin
            FR1 = 1;
            FR2 = 1;
            FR3 = 1;
            AFR = 1;
        end
    endcase
end

endmodule

testbenchs/water_tb.v
`timescale 1ns / 1ps

module water_reservoir_controller_tb;

    reg S1, S2, S3;
    reg clk, reset;

    wire FR1, FR2, FR3, AFR;

    water_reservoir_controller uut (
        .S1(S1), .S2(S2), .S3(S3),
        .FR1(FR1), .FR2(FR2), .FR3(FR3), .AFR(AFR),
        .clk(clk), .reset(reset)
    );

    initial begin
        clk = 0;
        forever #5 clk = ~clk;  // 100MHz clock
    end

    initial begin
        $dumpfile("water_sim.vcd");
        $dumpvars(0, water_reservoir_controller_tb);
    end

    initial begin
        S1 = 1; S2 = 1; S3 = 1;
        reset = 1;
        #10 reset = 0;

        #20 $display("Test case 1: Above S3");
        #10 if (FR1 == 0 && FR2 == 0 && FR3 == 0 && AFR == 0)
            $display("Test case 1 passed");
        else
            $display("Test case 1 failed");

        #20 $display("Test case 2: Between S3 and S2");
        S3 = 0;
        #10 if (FR1 == 1 && FR2 == 0 && FR3 == 0 && AFR == 0)
            $display("Test case 2 passed");
        else
            $display("Test case 2 failed");

        #20 $display("Test case 3: Between S2 and S1");
        S2 = 0;
        #10 if (FR1 == 1 && FR2 == 1 && FR3 == 0 && AFR == 0)
            $display("Test case 3 passed");
        else
            $display("Test case 3 failed");

        #20 $display("Test case 4: Below S1");
        S1 = 0;
        #10 if (FR1 == 1 && FR2 == 1 && FR3 == 1 && AFR == 1)
            $display("Test case 4 passed");
        else
            $display("Test case 4 failed");

        #20 $display("Test case 5: Back to Between S2 and S1");
        S1 = 1;
        #10 if (FR1 == 1 && FR2 == 1 && FR3 == 0 && AFR == 0)
            $display("Test case 5 passed");
        else
            $display("Test case 5 failed");

        #20 $finish;
    end

endmodule

water/water_sim.vcd
$date
	Mon Jul 22 17:14:12 2024
$end
$version
	Icarus Verilog
$end
$timescale
	1ps
$end
$scope module water_reservoir_controller_tb $end
$var wire 1 ! FR3 $end
$var wire 1 " FR2 $end
$var wire 1 # FR1 $end
$var wire 1 $ AFR $end
$var reg 1 % S1 $end
$var reg 1 & S2 $end
$var reg 1 ' S3 $end
$var reg 1 ( clk $end
$var reg 1 ) reset $end
$scope module uut $end
$var wire 1 % S1 $end
$var wire 1 & S2 $end
$var wire 1 ' S3 $end
$var wire 1 ( clk $end
$var wire 1 ) reset $end
$var reg 1 $ AFR $end
$var reg 1 # FR1 $end
$var reg 1 " FR2 $end
$var reg 1 ! FR3 $end
$var reg 2 * current_state [1:0] $end
$var reg 2 + next_state [1:0] $end
$upscope $end
$upscope $end
$enddefinitions $end
#0
$dumpvars
b0 +
b0 *
1)
0(
1'
1&
1%
0$
0#
0"
0!
$end
#5000
1(
#10000
0(
0)
#15000
1(
#20000
0(
#25000
1(
#30000
0(
#35000
1(
#40000
0(
#45000
1(
#50000
0(
#55000
1(
#60000
b1 +
0(
0'
#65000
1#
b1 *
1(
#70000
0(
#75000
1(
#80000
0(
#85000
1(
#90000
b10 +
0(
0&
#95000
1"
1#
b10 *
1(
#100000
0(
#105000
1(
#110000
0(
#115000
1(
#120000
b11 +
0(
0%
#125000
1$
1!
1"
1#
b11 *
1(
#130000
0(
#135000
1(
#140000
0(
#145000
1(
#150000
b10 +
0(
1%
#155000
0$
0!
1"
1#
b10 *
1(
